CODE_STRUCTURE.rst
MANIFEST.in
README.rst
development.txt
requirements.txt
setup.cfg
setup.py
dacareux_httpbin/__init__.py
dacareux_httpbin/client.py
dacareux_httpbin/console.py
dacareux_httpbin/version.py
dacareux_httpbin.egg-info/PKG-INFO
dacareux_httpbin.egg-info/SOURCES.txt
dacareux_httpbin.egg-info/dependency_links.txt
dacareux_httpbin.egg-info/entry_points.txt
dacareux_httpbin.egg-info/not-zip-safe
dacareux_httpbin.egg-info/requires.txt
dacareux_httpbin.egg-info/top_level.txt